README.md
pyproject.toml
setup.py
hikari_tanchi.egg-info/PKG-INFO
hikari_tanchi.egg-info/SOURCES.txt
hikari_tanchi.egg-info/dependency_links.txt
hikari_tanchi.egg-info/requires.txt
hikari_tanchi.egg-info/top_level.txt
tanchi/__init__.py
tanchi/autocompletion.py
tanchi/commands.py
tanchi/conversion.py
tanchi/parser.py
tanchi/types.py