Metadata-Version: 2.1
Name: hikari-tanchi
Version: 1.3.4
Summary: A signature parser for hikari's command handler tanjun.
Home-page: https://github.com/thesadru/tanchi
Author: thesadru
Author-email: thesadru@gmail.com
License: UNKNOWN
Keywords: hikari
Platform: UNKNOWN
Classifier: Development Status :: 4 - Beta
Classifier: Intended Audience :: Developers
Classifier: Natural Language :: English
Classifier: Operating System :: OS Independent
Classifier: Programming Language :: Python :: 3.9
Classifier: Programming Language :: Python :: 3.10
Classifier: Topic :: Communications :: Chat
Classifier: Topic :: Internet :: WWW/HTTP
Classifier: Topic :: Software Development :: Libraries
Classifier: Topic :: Software Development :: Libraries :: Python Modules
Classifier: Topic :: Utilities
Classifier: Typing :: Typed
Requires-Python: >=3.9.0
